dftbplus_step/__init__.py
dftbplus_step/__main__.py
dftbplus_step/_version.py
dftbplus_step/band_structure.py
dftbplus_step/band_structure_parameters.py
dftbplus_step/band_structure_step.py
dftbplus_step/base.py
dftbplus_step/choose_parameters.py
dftbplus_step/choose_parameters_parameters.py
dftbplus_step/choose_parameters_step.py
dftbplus_step/computational_models.py
dftbplus_step/dftbplus.py
dftbplus_step/dftbplus_parameters.py
dftbplus_step/dftbplus_step.py
dftbplus_step/dos.py
dftbplus_step/dos_parameters.py
dftbplus_step/dos_step.py
dftbplus_step/energy.py
dftbplus_step/energy_parameters.py
dftbplus_step/energy_step.py
dftbplus_step/installer.py
dftbplus_step/metadata.py
dftbplus_step/optimization.py
dftbplus_step/optimization_parameters.py
dftbplus_step/optimization_step.py
dftbplus_step/slako.py
dftbplus_step/tk_band_structure.py
dftbplus_step/tk_choose_parameters.py
dftbplus_step/tk_dftbplus.py
dftbplus_step/tk_dos.py
dftbplus_step/tk_energy.py
dftbplus_step/tk_optimization.py
dftbplus_step/data/configuration.txt
dftbplus_step/data/dftbplus.ini
dftbplus_step/data/metadata.json
dftbplus_step/data/properties.csv
dftbplus_step/data/references.bib
dftbplus_step/data/seamm-dftbplus.yml
dftbplus_step/data/spin-constants.json
dftbplus_step/data/slako/3ob/3ob-3-1/Br-Br.skf
dftbplus_step/data/slako/3ob/3ob-3-1/Br-C.skf
dftbplus_step/data/slako/3ob/3ob-3-1/Br-Ca.skf
dftbplus_step/data/slako/3ob/3ob-3-1/Br-Cl.skf
dftbplus_step/data/slako/3ob/3ob-3-1/Br-F.skf
dftbplus_step/data/slako/3ob/3ob-3-1/Br-H.skf
dftbplus_step/data/slako/3ob/3ob-3-1/Br-I.skf
dftbplus_step/data/slako/3ob/3ob-3-1/Br-K.skf
dftbplus_step/data/slako/3ob/3ob-3-1/Br-Mg.skf
dftbplus_step/data/slako/3ob/3ob-3-1/Br-N.skf
dftbplus_step/data/slako/3ob/3ob-3-1/Br-Na.skf
dftbplus_step/data/slako/3ob/3ob-3-1/Br-O.skf
dftbplus_step/data/slako/3ob/3ob-3-1/Br-P.skf
dftbplus_step/data/slako/3ob/3ob-3-1/Br-S.skf
dftbplus_step/data/slako/3ob/3ob-3-1/Br-Zn.skf
dftbplus_step/data/slako/3ob/3ob-3-1/C-Br.skf
dftbplus_step-2025.3.7.dist-info/AUTHORS.rst
dftbplus_step-2025.3.7.dist-info/LICENSE
dftbplus_step-2025.3.7.dist-info/METADATA
dftbplus_step-2025.3.7.dist-info/WHEEL
dftbplus_step-2025.3.7.dist-info/entry_points.txt
dftbplus_step-2025.3.7.dist-info/top_level.txt
dftbplus_step-2025.3.7.dist-info/RECORD
