Metadata-Version: 2.2
Name: dftbplus_step
Version: 2025.3.7
Summary: A SEAMM plug-in for DFTB+, a fast quantum mechanical simulation code.
Home-page: https://github.com/molssi-seamm/dftbplus_step
Author: Paul Saxe
Author-email: psaxe@molssi.org
License: BSD-3-Clause
Keywords: SEAMM,plug-in,flowchart,quantum,simulation,atomistic,DFTB+,DFTBplus,tight-binding,DFT
Platform: Linux
Platform: Mac OS-X
Platform: Unix
Platform: Windows
Classifier: Development Status :: 5 - Production/Stable
Classifier: Intended Audience :: Science/Research
Classifier: Topic :: Scientific/Engineering :: Chemistry
Classifier: Topic :: Scientific/Engineering :: Physics
Classifier: License :: OSI Approved :: BSD License
Classifier: Natural Language :: English
Classifier: Programming Language :: Python :: 3 :: Only
Classifier: Programming Language :: Python :: 3.8
Classifier: Programming Language :: Python :: 3.9
License-File: LICENSE
License-File: AUTHORS.rst
Requires-Dist: cms_plots
Requires-Dist: hsd
Requires-Dist: numpy
Requires-Dist: pandas
Requires-Dist: py-cpuinfo
Requires-Dist: seamm
Requires-Dist: seamm-exec
Requires-Dist: seamm_util
Requires-Dist: tabulate
Dynamic: author
Dynamic: author-email
Dynamic: classifier
Dynamic: description
Dynamic: description-content-type
Dynamic: home-page
Dynamic: keywords
Dynamic: license
Dynamic: platform
Dynamic: requires-dist
Dynamic: summary
